cmcccloudsdkcore/__init__.py
cmcccloudsdkcore/client.py
cmcccloudsdkcore/sdk_request.py
cmcccloudsdkcore/sdk_response.py
cmcccloudsdkcore/sdk_stream_request.py
cmcccloudsdkcore/sdk_stream_response.py
cmcccloudsdkcore/auth/__init__.py
cmcccloudsdkcore/auth/cache.py
cmcccloudsdkcore/auth/credentials.py
cmcccloudsdkcore/auth/internal.py
cmcccloudsdkcore/auth/provider.py
cmcccloudsdkcore/exceptions/__init__.py
cmcccloudsdkcore/exceptions/exception_handler.py
cmcccloudsdkcore/exceptions/exceptions.py
cmcccloudsdkcore/http/__init__.py
cmcccloudsdkcore/http/formdata.py
cmcccloudsdkcore/http/future_session.py
cmcccloudsdkcore/http/http_client.py
cmcccloudsdkcore/http/http_config.py
cmcccloudsdkcore/http/http_handler.py
cmcccloudsdkcore/http/primitive_types.py
cmcccloudsdkcore/http/progress.py
cmcccloudsdkcore/invoker/__init__.py
cmcccloudsdkcore/invoker/invoker.py
cmcccloudsdkcore/region/__init__.py
cmcccloudsdkcore/region/cache.py
cmcccloudsdkcore/region/provider.py
cmcccloudsdkcore/region/region.py
cmcccloudsdkcore/signer/__init__.py
cmcccloudsdkcore/signer/algorithm.py
cmcccloudsdkcore/signer/gm.py
cmcccloudsdkcore/signer/hkdf.py
cmcccloudsdkcore/signer/signer.py
cmcccloudsdkcore/utils/__init__.py
cmcccloudsdkcore/utils/core_utils.py
cmcccloudsdkcore/utils/filepath_utils.py
cmcccloudsdkcore/utils/http_utils.py
cmcccloudsdkcore/utils/six_utils.py
cmcccloudsdkcore/utils/string_utils.py
cmcccloudsdkcore/utils/time_utils.py
cmcccloudsdkcore/utils/xml_utils.py
cmcccloudsdkcore-0.0.1b0.dist-info/LICENSE
cmcccloudsdkcore-0.0.1b0.dist-info/METADATA
cmcccloudsdkcore-0.0.1b0.dist-info/WHEEL
cmcccloudsdkcore-0.0.1b0.dist-info/top_level.txt
cmcccloudsdkcore-0.0.1b0.dist-info/RECORD
